src/__init__.py
src/idosell/__init__.py
src/idosell/_common.py
src/idosell/api_request.py
src/idosell/cms/__init__.py
src/idosell/cms/_common.py
src/idosell/cms/_specs.py
src/idosell/cms/config_variables.py
src/idosell/cms/entries.py
src/idosell/cms/cpa/__init__.py
src/idosell/cms/cpa/_specs.py
src/idosell/cms/cpa/campaign.py
src/idosell/cms/cpa/cpa.py
src/idosell/cms/snippets/__init__.py
src/idosell/cms/snippets/_specs.py
src/idosell/cms/snippets/campaign.py
src/idosell/cms/snippets/cookies.py
src/idosell/cms/snippets/snippets.py
src/idosell/crm/__init__.py
src/idosell/crm/_common.py
src/idosell/crm/_specs.py
src/idosell/crm/clients.py
src/idosell/crm/crm.py
src/idosell/crm/deliveryaddress.py
src/idosell/crm/discounts.py
src/idosell/crm/externalcode.py
src/idosell/crm/giftcards.py
src/idosell/crm/membership.py
src/idosell/crm/newsletter.py
src/idosell/crm/payeraddress.py
src/idosell/crm/pricelists.py
src/idosell/crm/profitpoints.py
src/idosell/crm/provincelist.py
src/idosell/crm/tags.py
src/idosell/crm/vouchers.py
src/idosell/oms/__init__.py
src/idosell/oms/_common.py
src/idosell/oms/_specs.py
src/idosell/oms/orders.py
src/idosell/oms/packages.py
src/idosell/oms/payments.py
src/idosell/oms/refunds.py
src/idosell/oms/returns.py
src/idosell/oms/rma.py
src/idosell/oms/subscriptions.py
src/idosell/pim/__init__.py
src/idosell/pim/_common.py
src/idosell/pim/_specs.py
src/idosell/pim/menu.py
src/idosell/pim/responsibility.py
src/idosell/pim/sizecharts.py
src/idosell/pim/sizes.py
src/idosell/pim/warranties.py
src/idosell/pim/products/__init__.py
src/idosell/pim/products/_common.py
src/idosell/pim/products/_specs.py
src/idosell/pim/products/brands.py
src/idosell/pim/products/bundles.py
src/idosell/pim/products/categories.py
src/idosell/pim/products/collections.py
src/idosell/pim/products/descriptions.py
src/idosell/pim/products/groups.py
src/idosell/pim/products/images.py
src/idosell/pim/products/marketing.py
src/idosell/pim/products/miscs.py
idosell_api-0.8.1.1b1.dist-info/METADATA
idosell_api-0.8.1.1b1.dist-info/WHEEL
idosell_api-0.8.1.1b1.dist-info/licenses/LICENSE
idosell_api-0.8.1.1b1.dist-info/RECORD
