Metadata-Version: 2.4
Name: idosell-api
Version: 0.8.1.1b1
Summary: Python SDK for Idosell REST API
Project-URL: Homepage, https://github.com/mozan/idosell-python
Project-URL: Repository, https://github.com/mozan/idosell-python
Project-URL: Issues, https://github.com/mozan/idosell-python/issues
Project-URL: Documentation, https://github.com/mozan/idosell-python#readme
Author-email: Bartłomiej Moszyński <bartekm@gmail.com>
License-Expression: MIT
License-File: LICENSE
Keywords: api,client,cms,crm,ecommerce,idosell,oms,pim,rest,sdk,system,wms
Classifier: Development Status :: 4 - Beta
Classifier: Intended Audience :: Developers
Classifier: Operating System :: OS Independent
Classifier: Programming Language :: Python :: 3
Classifier: Programming Language :: Python :: 3.12
Classifier: Topic :: Internet :: WWW/HTTP
Classifier: Topic :: Software Development :: Libraries :: Python Modules
Classifier: Topic :: System :: Distributed Computing
Requires-Python: >=3.12
Requires-Dist: httpx>=0.27.0
Requires-Dist: pydantic>=2.1
Requires-Dist: python-dateutil>=2.9.0
Requires-Dist: python-dotenv>=1.1.1
